kg4cdo/Deductive_synthesis.py
kg4cdo/Ind_synthesis.py
kg4cdo/Load_comp_KG_hierarchy_generate_script.py
kg4cdo/Load_comp_KG_linear_generate_script.py
kg4cdo/Model_creation_hierarchy.py
kg4cdo/Model_creation_one_level.py
kg4cdo/Model_cusomised_creation_hierarchy.py
kg4cdo/__init__.py
kg4cdo-0.2.13.dist-info/METADATA
kg4cdo-0.2.13.dist-info/WHEEL
kg4cdo-0.2.13.dist-info/top_level.txt
kg4cdo-0.2.13.dist-info/RECORD
