Metadata-Version: 2.4
Name: kg4cdo
Version: 0.2.13
Summary: KG4CDO: A Knowledge Based Framework for Objects Models Synthesis
Home-page: https://github.com/kulikovia/KG4CDO
Author: kulikovia
Author-email: i.a.kulikov@gmail.com
Project-URL: GitHub, https://github.com/kulikovia/KG4CDO
Keywords: knowledge framework object model synthesis
Classifier: Programming Language :: Python :: 3.11
Classifier: License :: OSI Approved :: MIT License
Classifier: Operating System :: OS Independent
Requires-Python: >=3.6
Requires-Dist: requests>=2.25.1
Dynamic: author
Dynamic: author-email
Dynamic: classifier
Dynamic: description
Dynamic: description-content-type
Dynamic: home-page
Dynamic: keywords
Dynamic: project-url
Dynamic: requires-dist
Dynamic: requires-python
Dynamic: summary
